hubmap_sdk/__init__.py
hubmap_sdk/client.py
hubmap_sdk/collection.py
hubmap_sdk/dataset.py
hubmap_sdk/donor.py
hubmap_sdk/entity.py
hubmap_sdk/entitysdk.py
hubmap_sdk/epicollection.py
hubmap_sdk/publication.py
hubmap_sdk/sample.py
hubmap_sdk/sdk_helper.py
hubmap_sdk/searchsdk.py
hubmap_sdk/upload.py
hubmap_sdk-1.0.10.dist-info/LICENSE
hubmap_sdk-1.0.10.dist-info/METADATA
hubmap_sdk-1.0.10.dist-info/WHEEL
hubmap_sdk-1.0.10.dist-info/top_level.txt
hubmap_sdk-1.0.10.dist-info/RECORD
