Metadata-Version: 2.1
Name: hubmap-sdk
Version: 1.0.10
Summary: Python Client Libary to use HuBMAP web services
Author: Hubmap
Author-email: api-developers@hubmapconsortium.org
Keywords: HuBMAP Sdk,python
Classifier: Programming Language :: Python :: 3
Classifier: License :: OSI Approved :: MIT License
Classifier: Operating System :: OS Independent
Requires-Python: >=3.9
License-File: LICENSE
Requires-Dist: certifi==2021.10.8
Requires-Dist: chardet==4.0.0
Requires-Dist: idna==2.10
Requires-Dist: requests>=2.22.0
Requires-Dist: urllib3==1.26.7
